ditty/__init__.py
ditty/data.py
ditty/pipeline.py
ditty/trainer.py
ditty/utils.py
ditty-0.5.0.dist-info/LICENSE
ditty-0.5.0.dist-info/METADATA
ditty-0.5.0.dist-info/WHEEL
ditty-0.5.0.dist-info/top_level.txt
ditty-0.5.0.dist-info/RECORD
