Metadata-Version: 2.1
Name: ditty
Version: 0.5.0
Home-page: https://github.com/iantbutler01/ditty
Author: Ian T Butler (KinglyCrow)
Author-email: iantbutler01@gmail.com
License: Apache V2
Keywords: finetuning,llm,nlp,machine learning
License-File: LICENSE
Requires-Dist: accelerate
Requires-Dist: transformers
Requires-Dist: datasets
Requires-Dist: bitsandbytes
Requires-Dist: fire
Requires-Dist: peft
